MANIFEST.in
README.md
setup.py
SFlock.egg-info/PKG-INFO
SFlock.egg-info/SOURCES.txt
SFlock.egg-info/dependency_links.txt
SFlock.egg-info/entry_points.txt
SFlock.egg-info/requires.txt
SFlock.egg-info/top_level.txt
sflock/__init__.py
sflock/abstracts.py
sflock/config.py
sflock/exception.py
sflock/ident.py
sflock/main.py
sflock/misc.py
sflock/pick.py
sflock/compat/__init__.py
sflock/compat/magic.py
sflock/data/__init__.py
sflock/data/password.txt
sflock/data/poweriso.elf
sflock/data/zipjail.elf
sflock/data/win32/magic.mgc
sflock/data/win32/magic1.dll
sflock/data/win32/regex2.dll
sflock/data/win32/zlib1.dll
sflock/data/win64/libgnurx-0.dll
sflock/data/win64/magic.mgc
sflock/data/win64/magic1.dll
sflock/decode/__init__.py
sflock/decode/office.py
sflock/unpack/__init__.py
sflock/unpack/ace.py
sflock/unpack/bup.py
sflock/unpack/cab.py
sflock/unpack/daa.py
sflock/unpack/eml.py
sflock/unpack/msg.py
sflock/unpack/mso.py
sflock/unpack/office.py
sflock/unpack/pdf.py
sflock/unpack/rar.py
sflock/unpack/tar.py
sflock/unpack/zip.py
sflock/unpack/zip7.py