Metadata-Version: 1.0
Name: SFlock
Version: 0.3.10
Summary: Sample staging and detonation utility
Home-page: http://sflock.org/
Author: Hatching B.V.
Author-email: jbr@hatching.io
License: GPLv3
Platform: UNKNOWN
